birfi/__init__.py
birfi/birfi.py
birfi/utils.py
birfi-0.1.1.dist-info/licenses/LICENSE
birfi-0.1.1.dist-info/METADATA
birfi-0.1.1.dist-info/WHEEL
birfi-0.1.1.dist-info/top_level.txt
birfi-0.1.1.dist-info/RECORD
