Metadata-Version: 2.4
Name: birfi
Version: 0.1.1
Summary: Blind instrument response function identification from fluorescence decays.
Home-page: https://github.com/VicidominiLab/birfi
Author: Alessandro Zunino
Author-email: Alessandro Zunino <zuninoalessandro@gmail.com>
Project-URL: Homepage, https://github.com/VicidominiLab/birfi
Project-URL: Documentation, https://github.com/VicidominiLab/birfi/tree/main/examples
Classifier: Programming Language :: Python :: 3.7
Classifier: Programming Language :: Python :: 3.8
Classifier: Programming Language :: Python :: 3.9
Classifier: Programming Language :: Python :: 3.10
Classifier: Programming Language :: Python :: 3.11
Classifier: Programming Language :: Python :: 3.12
Classifier: Operating System :: OS Independent
Classifier: License :: OSI Approved :: GNU General Public License v3 or later (GPLv3+)
Requires-Python: >=3.7
License-File: LICENSE
Requires-Dist: numpy
Requires-Dist: scipy
Requires-Dist: matplotlib
Requires-Dist: torch
Provides-Extra: testing
Requires-Dist: tox; extra == "testing"
Requires-Dist: pytest; extra == "testing"
Requires-Dist: pytest-cov; extra == "testing"
Requires-Dist: pytest-qt; extra == "testing"
Requires-Dist: napari; extra == "testing"
Requires-Dist: pyqt5; extra == "testing"
Dynamic: license-file
